substrate/__init__.py
substrate/__main__.py
substrate/substrate.py
substrate/targets/__init__.py
substrate/targets/aws_stack.py
substrate/targets/docker_swarm.py
substrate/tools/__init__.py
substrate/tools/braid.py
substrate/tools/generic_tool.py
substrate/tools/hello_world.py
substrate/tools/nc_slicer.py
substrate/tools/ospray_studio.py
substrate/tools/tapestry.py
substrate/tools/tool.py
substrate/tools/tapestry/app/constants.js
substrate/tools/tapestry/app/index.html
substrate/tools/tapestry/app/css/style.css
substrate/tools/tapestry/app/js/arcball.js
substrate/tools/tapestry/app/js/gremlins.min.js
substrate/tools/tapestry/app/js/gui.js
substrate/tools/tapestry/app/js/main.js
substrate/tools/tapestry/app/js/math.js
substrate/tools/tapestry/app/js/smooth.js
substrate/tools/tapestry/app/js/sylvester.js
substrate/tools/tapestry/app/js/tapestry.js
substrate/tools/tapestry/app/js/testing.js
substrate/tools/tapestry/app/js/tools.js
substrate/tools/tapestry/config/data.json
seelabutk_substrate-1.9.0.dist-info/LICENSE
seelabutk_substrate-1.9.0.dist-info/METADATA
seelabutk_substrate-1.9.0.dist-info/WHEEL
seelabutk_substrate-1.9.0.dist-info/entry_points.txt
seelabutk_substrate-1.9.0.dist-info/top_level.txt
seelabutk_substrate-1.9.0.dist-info/RECORD
