Metadata-Version: 2.1
Name: seelabutk-substrate
Version: 1.9.0
Summary: Automatically deploys visualization services via Docker Swarm
Author-email: John Duggan <jduggan1@utk.edu>
License: CC-BY-4.0
Project-URL: Homepage, https://github.com/seelabutk/substrate/
Classifier: Programming Language :: Python :: 3
Classifier: Operating System :: OS Independent
Requires-Python: >=3.7
License-File: LICENSE
Requires-Dist: aws-cdk-lib (~=2.24.1)
Requires-Dist: constructs (~=10.1.11)
Requires-Dist: docker (~=5.0.3)
Requires-Dist: paramiko (~=2.11.0)
Requires-Dist: PyYAML (~=6.0)
Requires-Dist: requests (~=2.27.1)
